[{"id": 1, "segment_id": 5, "user_id": "ali", "description": "Air hitam berbau", "severity": "medium", "points_earned": 25, "severity_weight": 2, "status": "pending", "verifications": [{"user_id": "bob", "tier": 1, "weight": 1, "timestamp": "2026-06-08T17:37:01.922277"}, {"user_id": "carol", "tier": 1, "weight": 1, "timestamp": "2026-06-08T17:37:01.989802"}, {"user_id": "dave", "tier": 1, "weight": 1, "timestamp": "2026-06-08T17:37:02.045827"}, {"user_id": "eve", "tier": 1, "weight": 1, "timestamp": "2026-06-08T17:37:02.104485"}, {"user_id": "frank", "tier": 1, "weight": 1, "timestamp": "2026-06-08T17:37:02.166286"}, {"user_id": "grace", "tier": 1, "weight": 1, "timestamp": "2026-06-08T17:37:02.225807"}, {"user_id": "henry", "tier": 1, "weight": 1, "timestamp": "2026-06-08T17:37:02.293801"}, {"user_id": "ivan", "tier": 1, "weight": 1, "timestamp": "2026-06-08T17:37:02.350989"}, {"user_id": "jane", "tier": 1, "weight": 1, "timestamp": "2026-06-08T17:37:02.416852"}], "timestamp": "2026-06-08T17:37:01.862615"}]